tap_snowflake/__init__.py
tap_snowflake/connection.py
tap_snowflake/sync_strategies/__init__.py
tap_snowflake/sync_strategies/common.py
tap_snowflake/sync_strategies/full_table.py
tap_snowflake/sync_strategies/incremental.py
pipelinewise_tap_snowflake-3.0.0.dist-info/LICENSE
pipelinewise_tap_snowflake-3.0.0.dist-info/METADATA
pipelinewise_tap_snowflake-3.0.0.dist-info/WHEEL
pipelinewise_tap_snowflake-3.0.0.dist-info/entry_points.txt
pipelinewise_tap_snowflake-3.0.0.dist-info/top_level.txt
pipelinewise_tap_snowflake-3.0.0.dist-info/RECORD
