Metadata-Version: 2.1
Name: pipelinewise-tap-snowflake
Version: 3.0.0
Summary: Singer.io tap for extracting data from Snowflake - PipelineWise compatible
Home-page: https://github.com/transferwise/pipelinewise-tap-snowflake
Author: TransferWise
License: UNKNOWN
Platform: UNKNOWN
Classifier: License :: OSI Approved :: Apache Software License
Classifier: Programming Language :: Python :: 3 :: Only
License-File: LICENSE
Requires-Dist: pipelinewise-singer-python (==1.*)
Requires-Dist: snowflake-connector-python[pandas] (==2.7.*)
Requires-Dist: pendulum (==1.2.0)
Provides-Extra: test
Requires-Dist: pylint (==2.8.*) ; extra == 'test'
Requires-Dist: pytest (==6.2.*) ; extra == 'test'
Requires-Dist: pytest-cov (==2.12.*) ; extra == 'test'
Requires-Dist: unify (==0.5) ; extra == 'test'
